[
    {
        "tipo": "compra",
        "ticker": "BTC",
        "cantidad": 0.0011469994494402642,
        "monto_usdt": 100.0,
        "precio_unitario": 87184
    },
    {
        "tipo": "compra",
        "ticker": "BTC",
        "cantidad": 0.00011468547508458054,
        "monto_usdt": 10.0,
        "precio_unitario": 87195
    },
    {
        "tipo": "compra",
        "ticker": "BTC",
        "cantidad": 0.00011462106276649397,
        "monto_usdt": 10.0,
        "precio_unitario": 87244
    },
    {
        "tipo": "compra",
        "ticker": "BTC",
        "cantidad": 0.00011462106276649397,
        "monto_usdt": 10.0,
        "precio_unitario": 87244
    },
    {
        "tipo": "venta",
        "ticker": "BTC",
        "cantidad": 0.001,
        "monto_usdt": 87.244,
        "precio_unitario": 87244
    }
]